pulpcore/cli/deb/__init__.py
pulpcore/cli/deb/content.py
pulpcore/cli/deb/distribution.py
pulpcore/cli/deb/publication.py
pulpcore/cli/deb/py.typed
pulpcore/cli/deb/remote.py
pulpcore/cli/deb/repository.py
pulpcore/cli/deb/locale/de/LC_MESSAGES/messages.mo
pulp_cli_deb-0.4.2.dist-info/METADATA
pulp_cli_deb-0.4.2.dist-info/WHEEL
pulp_cli_deb-0.4.2.dist-info/entry_points.txt
pulp_cli_deb-0.4.2.dist-info/top_level.txt
pulp_cli_deb-0.4.2.dist-info/RECORD
